rkguiv3/__init__.py
rkguiv3/core.py
rkguiv3/dialogs/__init__.py
rkguiv3/dialogs/file_dialogs.py
rkguiv3/dialogs/message_dialogs.py
rkguiv3/dialogs/pickers.py
rkguiv3/utils/__init__.py
rkguiv3/utils/animations.py
rkguiv3/utils/debug.py
rkguiv3/utils/drag_drop.py
rkguiv3/utils/live_reload.py
rkguiv3/widgets/__init__.py
rkguiv3/widgets/basic.py
rkguiv3/widgets/buttons.py
rkguiv3/widgets/containers.py
rkguiv3/widgets/dropdowns.py
rkguiv3/widgets/inputs.py
rkguiv3/widgets/media.py
rkguiv3/widgets/menus.py
rkguiv3/widgets/tables.py
rkguiv3/widgets/utilities.py
rkguiv3/widgets/web.py
rkguiv3-0.1.4.dist-info/METADATA
rkguiv3-0.1.4.dist-info/WHEEL
rkguiv3-0.1.4.dist-info/top_level.txt
rkguiv3-0.1.4.dist-info/RECORD
