Metadata-Version: 2.4
Name: rkguiv3
Version: 0.1.4
Summary: Comprehensive Tkinter-based GUI library
Author: 1001015dhh
License: MIT
Keywords: tkinter gui widgets ui toolkit
Classifier: Development Status :: 3 - Alpha
Classifier: Intended Audience :: Developers
Classifier: License :: OSI Approved :: MIT License
Classifier: Programming Language :: Python :: 3
Classifier: Programming Language :: Python :: 3.7
Classifier: Programming Language :: Python :: 3.8
Classifier: Programming Language :: Python :: 3.9
Classifier: Programming Language :: Python :: 3.10
Classifier: Operating System :: OS Independent
Classifier: Topic :: Software Development :: Libraries :: Python Modules
Classifier: Topic :: Software Development :: User Interfaces
Requires-Python: >=3.7
Requires-Dist: pillow
Requires-Dist: tkcalendar
Requires-Dist: python-vlc
Requires-Dist: cefpython3; platform_system == "Windows"
Dynamic: author
Dynamic: classifier
Dynamic: keywords
Dynamic: license
Dynamic: requires-dist
Dynamic: requires-python
Dynamic: summary
